[
  {
    "id": "cons-1784178853230",
    "full_name": "Test Client Hassaan",
    "email": "client@example.com",
    "phone": "+92 311 6647440",
    "subject": "Consultation integration test",
    "message": "Hello, I would like to build a full-stack portfolio dashboard application.",
    "created_at": "2026-07-16T05:14:13.229Z"
  },
  {
    "id": "cons-1784178828163",
    "full_name": "Test Client Hassaan",
    "email": "client@example.com",
    "phone": "+92 311 6647440",
    "subject": "Consultation integration test",
    "message": "Hello, I would like to build a full-stack portfolio dashboard application.",
    "created_at": "2026-07-16T05:13:48.162Z"
  },
  {
    "id": "cons-1783741745105",
    "name": "Consultation Client",
    "email": "client@example.com",
    "project_type": "Web Application",
    "message": "I need a dashboard.",
    "created_at": "2026-07-11T03:49:05.104Z"
  }
]